LICENSE.txt
MANIFEST.in
README.md
VERSION
setup.cfg
setup.py
./deepsim_btree/__init__.py
./deepsim_btree/behaviour.py
./deepsim_btree/constants.py
./deepsim_btree/leaves.py
./deepsim_btree/composites/__init__.py
./deepsim_btree/composites/composite.py
./deepsim_btree/composites/parallel_selector.py
./deepsim_btree/composites/parallel_sequence.py
./deepsim_btree/composites/rand_selector.py
./deepsim_btree/composites/rand_sequence.py
./deepsim_btree/composites/selector.py
./deepsim_btree/composites/sequence.py
./deepsim_btree/decorators/__init__.py
./deepsim_btree/decorators/condition.py
./deepsim_btree/decorators/decorator.py
./deepsim_btree/decorators/limit.py
./deepsim_btree/decorators/repeater.py
./deepsim_btree/decorators/status_flippers.py
deepsim_btree.egg-info/PKG-INFO
deepsim_btree.egg-info/SOURCES.txt
deepsim_btree.egg-info/dependency_links.txt
deepsim_btree.egg-info/requires.txt
deepsim_btree.egg-info/top_level.txt
test/test_deepsim_btree_import.py