Metadata-Version: 2.1
Name: deepsim-btree
Version: 0.1.2
Summary: A Behaviour Tree library for DeepSim Toolkit.
Home-page: https://github.com/aws-deepracer/deepsim/tree/main/deepsim_btree
Author: Amazon Web Services
License: Apache License 2.0
Keywords: ML RL Amazon AWS AI DeepSim
Platform: UNKNOWN
Classifier: Development Status :: 4 - Beta
Classifier: Intended Audience :: Developers
Classifier: Natural Language :: English
Classifier: License :: OSI Approved :: Apache Software License
Classifier: Programming Language :: Python
Classifier: Programming Language :: Python :: 3.6
Classifier: Programming Language :: Python :: 3.7
Classifier: Programming Language :: Python :: 3.8
Classifier: Programming Language :: Python :: 3.9
License-File: LICENSE.txt
